{
    "percentages": {
        "truth": 0,
        "falsity": 0,
        "uncertainty": 100
    },
    "verdict_label": "INCERTO",
    "explainability": {
        "summary": "Verdetto matematico: 0.0 punti per la conferma e 0.0 punti per la smentita.",
        "cross_check_result": "Punteggi -> Conferma: 0.0 | Confuta: 0.0",
        "strength_analysis": "Il calcolo si basa sulla somma del peso (affidabilità) della fonte moltiplicato per ogni evidenza testuale (chunk) trovata e classificata.",
        "consensus_level": "Nessuno",
        "next_step": "Raccogliere ulteriori fonti."
    },
    "top_sources": {
        "supporting": [],
        "conflicting": []
    },
    "analysis_tags": [
        "Calcolo Matematico",
        "INCERTO"
    ],
    "confidence_score": 80
}